hyperpixel2r/__init__.py
hyperpixel2r/__main__.py
hyperpixel2r-0.0.1.dist-info/LICENSE.txt
hyperpixel2r-0.0.1.dist-info/METADATA
hyperpixel2r-0.0.1.dist-info/WHEEL
hyperpixel2r-0.0.1.dist-info/top_level.txt
hyperpixel2r-0.0.1.dist-info/RECORD
