Metadata-Version: 2.1
Name: hyperpixel2r
Version: 0.0.1
Summary: Python driver for the HyperPixel 2" round LCD
Home-page: https://www.pimoroni.com
Author: Philip Howard
Author-email: phil@pimoroni.com
License: MIT
Project-URL: GitHub, https://www.github.com/pimoroni/hyperpixel2r-python
Keywords: Raspberry Pi
Platform: UNKNOWN
Classifier: Development Status :: 4 - Beta
Classifier: Operating System :: POSIX :: Linux
Classifier: License :: OSI Approved :: MIT License
Classifier: Intended Audience :: Developers
Classifier: Programming Language :: Python :: 2.7
Classifier: Programming Language :: Python :: 3
Classifier: Topic :: Software Development
Classifier: Topic :: Software Development :: Libraries
Classifier: Topic :: System :: Hardware
Requires-Python: >= 2.7
Requires-Dist: smbus2
